majordome/__init__.py
majordome/common.py
majordome/combustion/__init__.py
majordome/combustion/analysis.py
majordome/simulation/__init__.py
majordome/simulation/fluent.py
majordome-0.4.5.dist-info/licenses/LICENSE
majordome-0.4.5.dist-info/METADATA
majordome-0.4.5.dist-info/WHEEL
majordome-0.4.5.dist-info/top_level.txt
majordome-0.4.5.dist-info/RECORD
