Metadata-Version: 2.4
Name: majordome
Version: 0.4.5
Summary: General utilities for scientific Python and numerical simulation.
Author-email: Walter Dal'Maz Silva <walter.dalmazsilva@gmail.com>
License-Expression: MIT
Project-URL: Homepage, https://github.com/wallytutor/python-majordome
Project-URL: Documentation, https://wallytutor.github.io/python-majordome/
Project-URL: Repository, https://github.com/wallytutor/python-majordome.git
Project-URL: Issues, https://github.com/wallytutor/python-majordome/issues
Keywords: scientific,simulation,utilities,python
Classifier: Development Status :: 3 - Alpha
Classifier: Intended Audience :: Science/Research
Classifier: Topic :: Scientific/Engineering
Classifier: Programming Language :: Python :: 3.12
Classifier: Programming Language :: Python :: 3.13
Requires-Python: >=3.12
License-File: LICENSE
Requires-Dist: cantera>=3
Requires-Dist: matplotlib>=3
Requires-Dist: numpy>2
Requires-Dist: scipy>=1.15
Requires-Dist: pandas>=2.2
Requires-Dist: pyparsing>=3
Requires-Dist: pyvista>=0.44
Requires-Dist: pyyaml>=6
Dynamic: license-file
